MANIFEST.in
README.md
setup.cfg
setup.py
lib/iugu/__init__.py
lib/iugu/base.py
lib/iugu/config.py
lib/iugu/customers.py
lib/iugu/errors.py
lib/iugu/invoices.py
lib/iugu/merchant.py
lib/iugu/plans.py
lib/iugu/subscriptions.py
lib/iugu/tests.py
lib/iugu/utils.py
lib/iugu/version.py
lib/iugu_python.egg-info/PKG-INFO
lib/iugu_python.egg-info/SOURCES.txt
lib/iugu_python.egg-info/dependency_links.txt
lib/iugu_python.egg-info/top_level.txt