Metadata-Version: 1.1
Name: iugu-python
Version: 0.9.5-1
Summary: This package is an idiomatic python lib to work with Iugu service
Home-page: https://github.com/horacioibrahim/iugu-python
Author: Horacio Ibrahim
Author-email: horacioibrahim@gmail.com
License: Apache License
Download-URL: https://github.com/horacioibrahim/iugu-python/tarball/master
Keywords: iugu,rest,payment
Platform: UNKNOWN
Classifier: Development Status :: 5 - Production/Stable
Classifier: Intended Audience :: Developers
Classifier: Natural Language :: English
Classifier: Operating System :: OS Independent
Classifier: Programming Language :: Python
Classifier: Programming Language :: Python :: 2
Classifier: Programming Language :: Python :: 2.6
Classifier: Programming Language :: Python :: 2.7
Classifier: Topic :: Software Development :: Libraries :: Python Modules
